[
    {"id": 1, "nombre": "Teclado Marvo K606 RGB Layout Español","stock":10, "categoria": "periferico", "precio": 2700, "descripcion": "Teclado RGB con layout en Español simil mecanico.", "imagen": "https://www.maximus.com.ar/Temp/App_WebSite/App_PictureFiles/Items/K606-SP_800.jpg"},
    {"id": 2, "nombre": "Mouse Thermaltake Neros RGB 3200 Dpi","stock":3, "categoria": "periferico", "precio": 4500, "descripcion": "Mouse RGB con 3200 DPI para ser un verdadero gamer.", "imagen": "https://www.maximus.com.ar/Temp/App_WebSite/App_PictureFiles/Items/EMONRRWDOTBK_800.jpg"},
    {"id": 3, "nombre": "CPU Cooler Darkflash Darkair Black Fixed RGB","stock": 5, "categoria": "componentes", "precio": 7200, "descripcion": "Cooler RGB de 1300RPM compatible con AMD e INTEL", "imagen": "https://www.maximus.com.ar/Temp/App_WebSite/App_PictureFiles/Items/Darkair-Black_800.jpg"},
    {"id": 4, "nombre": "Mouse Pad Logitech XL Lavanda","stock":7, "categoria": "periferico", "precio": 3800, "descripcion": "Mousepad XL color Lavanda ultra-rapido, ideal para shooters y moba.", "imagen": "https://www.maximus.com.ar/Temp/App_WebSite/App_PictureFiles/Items/956-000036_800.jpg"},
    {"id": 5, "nombre": "Webcam Redragon GW600 Fobos 720p","stock":5, "categoria": "periferico", "precio": 5700, "descripcion": "WebCam para streamers o reuniones virtuales, graba a 720p y tiene microfono incorporado", "imagen": "https://www.maximus.com.ar/Temp/App_WebSite/App_PictureFiles/Items/6950376772275_800.jpg"},
    {"id": 6, "nombre": "Auricular Genesis Neon 600 RGB Black","stock":15, "categoria": "periferico", "precio": 9500, "descripcion": "Auricular RGB con Jack de 3.5mm con tipo de copa On-Ear. Ideal para estar horas jugando sin molestias", "imagen": "https://www.maximus.com.ar/Temp/App_WebSite/App_PictureFiles/Items/NSG-1656_800.jpg"}
]